encrypted_id/__init__.py
encrypted_id/models.py
django_encrypted_id_cryptography-1.1.0.dist-info/LICENSE
django_encrypted_id_cryptography-1.1.0.dist-info/METADATA
django_encrypted_id_cryptography-1.1.0.dist-info/WHEEL
django_encrypted_id_cryptography-1.1.0.dist-info/top_level.txt
django_encrypted_id_cryptography-1.1.0.dist-info/zip-safe
django_encrypted_id_cryptography-1.1.0.dist-info/RECORD
