Metadata-Version: 1.2
Name: django-encrypted-id-cryptography
Version: 1.1.0
Summary: Encrypted IDs for Django Models
Home-page: https://github.com/slinkymanbyday/django-encrypted-id-cryptography
Author: Sean Meyer
Author-email: slinkymabyday@gmail.com
Maintainer: Sean Meyer
Maintainer-email: slinkymabyday@gmail.com
License: BSD
Keywords: Django,Web
Platform: UNKNOWN
Classifier: Development Status :: 5 - Production/Stable
Classifier: Intended Audience :: Developers
Classifier: Intended Audience :: End Users/Desktop
Classifier: Intended Audience :: System Administrators
Classifier: Intended Audience :: Information Technology
Classifier: Intended Audience :: Other Audience
Classifier: Natural Language :: English
Classifier: Operating System :: OS Independent
Classifier: Operating System :: POSIX :: Linux
Classifier: Operating System :: Microsoft :: Windows
Classifier: Operating System :: MacOS :: MacOS X
Classifier: Programming Language :: Python
Classifier: Programming Language :: Python :: 2.7
Classifier: Programming Language :: Python :: 3.5
Classifier: Programming Language :: Python :: 3.7
Classifier: Programming Language :: Python :: Implementation :: CPython
Classifier: Topic :: Software Development
